{
"cts6lrp3uh2rkzins2owclt3":["31esfand","خارِ مغیلان"],
"bhvx2fcezk45fosm6nkvhhgd":["aliesfandiari","Ali Esfandiari"],
"7wkhn24r2egq7ao4u6fqcscu":["enfermeiro","Enfermeiro da ESF"],
"6umunhhxudrshuwrzwheieeg":["esfiart","Steph ✨"],
"bq7wmc3p6ebxlrnhzgw5myoc":["esfletcher","Elizabeth Fletcher"],
"fpyi5b7jvdmfkzo57r2tba2i":["esfjord","Eric/Fjord"],
"wdqckmcucszvidoyr435qu5x":["esfinn","Emily Finn"],
"wqlfkttarslb7heevxdcxr5z":["esfio","Every SpongeBob Frame In Order"],
"3pl7kn2q3saz2iakjhqkai4y":["esfahan","Esfahan | اصفهان"],
"ljthke2uqvatom2grvowu7ik":["esfanx","Kaël-Esfandiar 🌈 "],
"joiozpr4l5fnrz6wse4vhs4x":["esfandyari11","Mohammad Esfandyari "],
"qdydb5rplszoyxtr3ozq3yyh":["esfandiar","Esfandiar"],
"oyetgl6lufxph4vj5m44z2s4":["esfandiari","Rouzbeh Esfandiari "],
"uir5iyfbjncdpgx5k7iqxgfc":["esfolaxoxota","pitel"],
"dui2qgfpvyhg2fjhiko2wwuu":["esfdogma","Elizabeth S-F"],
"qgmoyrcw35k5hij75bnomiby":["esfahani","Hosein Esfahani"],
"fsuqauilb4scp7eqb73bo7jg":"esfinge",
"umug3iow5aaqaodpbjqrd24x":"esf",
"jnxmfucuegxw5dmec5ow3vgf":"esfemboy",
"qmwqfqhz2y2u4dnk3lzd3ojq":["esfera","Esfera"],
"4hgv6lbzsecns7qzvtapastp":["esfriou","caia"],
"jzpzfmvfdlp3cxedgbfefyv7":["esfb","E Scot Fuller-Beatty"],
"ocqciovp7ouzelsadpaexbzu":"esfxra",
"u5qcagda3zqy6rymliv6gcon":["esfir","Esfir! 💖"],
"sbpeg6hqeywuyrxr3x5vvst7":["esfirmwd","Esfir"],
"kx3lsbasersruwol4b3ykjff":["esfer","Veronica Cosmic"],
"7ez45qmsweuzj4vaklt64ocl":["esfandyar26","Mojtaba Esfandyar "],
"ww3nn4r2tflsf4xqkl2pqdwt":"esfelt",
"fpsil36io5cqdbtmm7ytrslc":["glog-esfj","왜노자 갱"],
"r7buebrhfaayl5g6u5tzvadh":["helenesfandiary","Helen Esfandiary "],
"xwp2elhvnawhnv7k4qbvnmjk":["kalibanlizer","Esfinge Bongadora 2.0"],
"ilchho65s36bg2nksor65unc":["mahdad","Mahdad Jafarzadeh Esfahani"],
"uk4k5vjp7kth3hnxov6eyea6":["mehdisfandiary","Mehdi Esfandiary"],
"w43qyjtevnaykigtzfikl673":["mehdighaedi","Mehdi_esf"],
"nqkgtcjqe536oiylwmb57r7f":["mona1358","Mona Esfahani"],
"7o6tru7lkiexnfjyho7uftd6":["saami","Sam Esfandiari "],
"7o3evg6wcszydxwbvmfc4ukb":["yarbatman","Esfandyar Batmanghelidj"]
}
