{
"blhlsp52jdvb2z6zro7ibi5q":["akasfan","esh"],
"xbpvvu4dwzmwi7xpan7ub56d":["ayeshaxiv","esha ૮꒰ ˶• ༝ •˶꒱ა"],
"bjndamicqvusxhhz2bdswkfd":["bathingonmars","esher"],
"jtbew74rizl252h3ywexgx5z":["cesmustache","a/k/a Craig Esherick's Mustache"],
"r3o5d2vxm3iyseanr43o6aof":["deepsealily","esha"],
"z6snpla7f5otym73kq6vlgi3":["desh182","Darren Eshenour"],
"7gla5lts3sapmik5qc63d3r2":["eshjolly","Eshin Jolly"],
"cfn4rftrnpb3i5oc4bcw74tp":["eshalegal","Esha"],
"cronmhiv462ngu7726eyu3mk":["esherukweku","Esheru"],
"efbccvrse4rp6oldncpqtojb":["eshm","Gavin"],
"gz6ptt6kyrjzto7446ptep6r":["eshficaddict","Esh"],
"htqx4yapholzp65wymwh2xuy":["eshumarneedi.tech","Eshu Marneedi"],
"jukhfgtju4zqpchwbk57x2ta":["eshil","سِدى "],
"ktwnd3gh5pfqnj2yphvmvpvh":["eshap","Evan Shapīro"],
"mmi7oosypndeogwut6bd6unt":["eshmimdalet","KaLMan SaFas"],
"pjreohyatmpkuq7jeobkcs3j":["eshonborn","Eric Shonborn"],
"s4wmjbqzefaxwc3taubtlemx":["esherzje","Herzje"],
"xsc3os4lyegevu63xhem5noa":["eshpur","eshpur"],
"zdoraz74u2uvoo22dlkcqc3o":["eshiede"," Eshie de Ecchi~🔞"],
"2jmlilrxvhf4kqvns7gfozei":["esh","Ehsan Shahabi"],
"tthf54lvidiiccdrpdqusvnh":["eshioji","Enno Shioji"],
"btwzxms7r5f5coydphrxpt6m":["eshita","Eshita "],
"wtk3iwla3p5lulcimy5yu37t":["esha","Esha"],
"lxksbz3p6fo24roi2xnmkrez":["eshan","Eshan"],
"t4omxd7sa6ximjerv5lsfjvg":["esh.dev","Eric Hammond"],
"xpjt2al6jkr3ndupwqqcdbqf":["esharp.net","Eyvonne Sharp"],
"fcdrvr6qclsejtv3pf35xx4r":["esherick","Kevin"],
"ewnmv4d7at4o5cjxanaa4xoq":["eshanxyz","Eshan"],
"dokvtlxgq4i7t2447uvkvq2e":["eshara0mode","es原"],
"gx4x5pd6jwebi7csdnet7mnh":"eshgh",
"d7vf5jdp3vyi3c3hkc5bhw3c":["eshara","Eshara"],
"mzgp3e22bfxxk7gkqdxph2lf":["eshugs","Emily Shugerman"],
"5z6v2etnrmj7tht7b4r5qehn":["eshadlow","Eden Shadlow"],
"nxhtvysdkffb33meoiwn3mws":["eshoeteric","No Hot Rad Wife"],
"pzzudnwlvz56n2oeaiax5rkh":"eshakhnovskiy",
"35kh2wcljn7fmtyferbqt2nw":["eshaknows","Esha Knows ✨️👩🏾‍💻💬"],
"db235swjgwd7wltnkkuqo4gv":["esharp","𝄆E Sharp 👻🍂𝄇"],
"rzvmdojjy4flkaidpx3wt4wj":"eshagh",
"g4itrwv6oe4ybw4e7t6azwxi":["eshete","Eshèté Bekele"],
"fl4qn2dfvnqgkk3tkwvegxuw":["eshirin","Elham Shabahat"],
"qotsuc6bnpa5ljemmnavnx65":"eshynes",
"afwnl3y4jkrosfx66arff7y7":"eshevek",
"3n4ywoiat3q3pkx7cfi6cy6u":["eshwarmaddineni","Eshwar Maddineni"],
"mn637g2jwqvsxb6vkvyk7iq3":["eshow","Mister E-Show"],
"ccmmrsiw4ru5dom6io6zinj5":"eshorvor",
"lntobkuctgizy7j5rn7gdrdp":["eshani","eshani"],
"xgoryuxcx5f2uhkdmokisz7j":["esherhouse","tiff2.0"],
"gea3537g42xfb2b6lfyamvi3":["eshh","esh"],
"srr5vp27uexsto7tc6agl3mn":["eshuman","Shu"],
"mm2akus6ishmr6pplz5skrln":["esherowski","Elizabeth Sherowski"],
"camqufxr7hbqiv5bxybvrxdd":"eshytle",
"jhew53bevjxdqotiin4bogy6":["esheninger","Eric Sheninger"],
"wp5lxg3ma24qhrxohwc2nsmw":"esheldon",
"f3gylhfvopughure3ieb456e":["eshtir","Markus Urban"],
"cs2dw3hgqbwo7ojmikzuwmlj":["eshumains","Eshu"],
"4gxxvbvwaj2syu2acusnt27k":"esh22",
"eavrg2mw72bbqtc4kzpdrlmw":"esherry",
"k63zys3zwqn2wjdsgbwrg5pd":["esherwood","Emily Sherwood"],
"vy4avsxydoerzfw5bwumovs2":["esheislife","Eshe ☥ 🇺🇦"],
"xizocpo3ofpasw4e77nnflxr":"eshader",
"3ggx3zcqsedldo6ftsbzxjee":["esherjackal","Esher"],
"kf7owuee34ptixrz3cytxmvr":["eshanisurya","Eshani Surya"],
"ufvy6mg2epkdcdsqiykgqpqc":"eshipmit",
"nri5p4qtj5urwwh6niv2mxie":"eshishkin",
"wkpsld65gvidst5gokwaprko":["eshuchart","Ethan S"],
"aul3dmjcvb3st36mfsfkjtwd":"eshward",
"ddcgcsqwrekfv7zk6fkqicb4":["eshivak","Eric Shivak"],
"ch4m5rocjvnjy5sw6fwdkyal":["eshaanmathur.com","Eshaan Mathur"],
"qropmz2a4q5q4h7drdmg4n2r":["eshcetera","E Salvador Hernandez"],
"oub75twlq7vp3iwa3peboiaf":["eshaolang","Eshaolang"],
"dtyzt5mimnifu3q5mcw4ajm5":"eshyell",
"owvg6rdkhidx56hudol6raoc":["eshay","sdoin"],
"n6jbc24h5llnjvfes6ar4mch":"eshiilon3",
"zoe7fmyfbh75hwhznxst2jtd":"eshlox",
"c2ilbxndiuhf6dloqwv7n3is":["eshkebab","Esh"],
"wkpl4o6lbbdpdcutd5yeen33":"eshwar",
"f6blrqukd2kkyvkjf5cvdczs":["esheby","E. Shabrina"],
"5u7kseoc5oxckx3evf42nqxo":["esheah","Esheah"],
"6gcdbr4boxmdivzwouslrp7m":"eshiilon0",
"quenyd6oeka4y3ltp3fx7gyj":["eshie","H"],
"vpwu4yzdn4qofldrh3bj62cm":"eshaw43",
"gvjpxlxnak72chfgrnpimsfx":"eshap0",
"gxxx4utuiohbs5ryidey5qb3":["eshehdafah","Stella"],
"qv3tmd4jicqa5hsuehbkfwsq":"eshtar",
"o4t77wvo6xe3kgmwt5qbevcm":["eshol","petra von cunt is @Bluesky!"],
"cn3mgbhdeoogiwjsctbl7ml7":["eshanfotedar","Eshan Fotedar"],
"fqrkg472nobsnmu7q6ye6jbu":"eshas",
"euteb4ipdghldf2o7xod7jx6":"eshallinan",
"3osvfpvkouomnr35j4sdsjvw":["eshu8745","에슈"],
"26exgzen6jcjxbwgia2of7ze":["eshii","Eshii"],
"rj5a5ye3u3g3gxhksbcft4mh":["esho","EshO"],
"x7d72iiaexapxvjbqpuk3lja":"eshiley",
"r2govhpw3pato7sqixzt6etj":["eshun","Espresso"],
"ghd33lfxthzwtteb7slixtrh":"eshim",
"qei3c7vjusgaes7drfhcwfdi":"eshr",
"4uckrmntqttvejylusdksdde":["eshyria","Eshyria 🐺✨"],
"3gcktunzhj3tezfrcp7267iy":["esharc","e"],
"eva57c4etnhcindvuljskbth":["eshaeufche","Alexander"],
"ucdl6hunwmqwowuqtnmn3h4e":["eshirley","Beth"],
"2joqjkfttsqarnzedwvwhsyf":["eshaspark","Esha Swaroop"],
"jhdoqwj5n2ytuijy65xosw4t":["eshusho","eshusho"],
"vpvdtsgga3vbbf2yrllmrqsm":["esheyn","Esh"],
"geifv65usnqke7torhwactxn":["eshkin-matreshkin","Ёшкин-Матрёшкин"],
"u5do5mnajj5akxl2hxhfuj2k":["eshanthika","Eshanthika"],
"mxfj6q7i7uyfd2mghqsisffi":["eshogouki","叫ばない初号機"],
"5dr5n5hb4jxndxzk73j5yumz":["eshienett","Shien (Autumn Arc 🍂)"],
"nzrvcqa4zp2ya3kmdjxlcmdg":"eshvedunova",
"lwd7v7cm5jz7k4jryboql6t3":"eshiilon6",
"zo3hu5cbeancelfx7ezraiw3":"eshied",
"u2ujwbymtoo47i72nyfjxxc7":"eshiilon11",
"mviuf7q5lgh6j5rx7zdcfaua":["eshshiv","Esh"],
"n2k63ln2upszqzzx34y2gvnt":["eshlie","eshleelie"],
"3mhiz6onxiqkd3664hqfyt4z":"eshap7",
"zyr3qabxoroko3tlolvzfohf":["eshaq","Isaac"],
"gwcops6g3uxvsa5no26jiiql":["eshade","Eshade"],
"msumhsyyr7txv7vqlzuzweva":["eshinebyond","E-Shine/Byond"],
"b6qruffcj2ahxm2d7vscwhre":["eshanas","Esha Nas 🔞"],
"o57c65yp5airrt4tzw2airc5":["eshmael","Daniel Dobbelstein"],
"cpqzk3mlnrphg3ik2eofcqne":["eshedlee","LeeE"],
"bufnkase5mvtcarhlagroolb":["eshmoneycoach","Elizabeth "],
"lzn7qzcsa4mtwdquhgffxtqt":["impactbasin","Henry Eshbaugh"],
"f756s3rwx63ebtoz2jc475wh":["j1esheng","j1esheng"],
"s7h755lmbwb5vg6h46ctdkh4":["kristeneshleman","Kristen Eshleman"],
"fhmvc3tu5kq4vl6j2jevjyzz":["marcesher","Marc Esher"],
"pwcx3uv4u7vaf37t3t6ngau5":["massa59","ESHITA Masayuki 江下雅之"],
"dlfzczsjgwjtng3wx63gvkww":["meakitty","Mea'eshana PhoenixFire"],
"7fr6mqxuayznjvmb5hn3s47e":["minsvenska","Jay-esh"],
"aqbgnyfnqh27hwepnmf6ybhc":["nataneshustrom","Natan eshu Strom"],
"ljncpzosf472pk3dielawit5":["natsumieshima","Natsumi Eshima "],
"yxdcsoc3hrhx24j5wjjwe4pg":["okheshivar","Okh Eshivar "],
"vfw5bokdy7ka2pqgivb5bgun":["orioneshel","Orion Eshel"],
"fmqe53wb37bb4aqsfri5emgi":["philyaoisopher","esh"],
"6sbr6osllb7gevnzdwhz2ats":["richhomieesh","Eazy Esh"],
"nvbhgkf2xbspeuo543wtctap":["royaesh455","Roya-esh455💞☕️💌"],
"f3nkcingxpinhwe3ys5ut5vj":["sarvesh","sar\\/esh"],
"eltkf4su3swkulkxxqe47dbe":["slimsteve","Stephen Eshun "],
"rztokk4vmohi24z5syphdlms":["thisissolmaz","solmaz eshraghi "],
"53ndukhxbbxuqfkkwofy56ow":["thecoffeekind","Esha"],
"pw6qamvnqnotezqwefl27zoa":["vornyvalacore","Valacore Eshima Vornia "]
}
