{
"kcwyebhyyrjko4t5ayamadpg":["charleseuka","Charles Euka"],
"6qvmqaxoyhey3if263zc47zi":["eukadanz","Eukadanz"],
"6ydp6kiuowsocihvpaweinmy":["eukrasia","amu!!"],
"pyu574txrjxzriyz5cgrxax4":["eukevin","Kevin "],
"tcxahka2pez7qq7jvpbw4mpw":["eukristian","Kristian"],
"bmlkmrw7n2nzq3qyatizlofh":"eukomos",
"bgduckzj7uwswhdui4a4ge77":["eukayozineo","Kayo"],
"fg7kx4z43ecvpe57kefpfzeo":["eukiecurr","Eukie"],
"xwzdktb5aif3u3s25me5m4q7":["eukara","Marco Cawthorne"],
"f2tm6pe2rsaklvs4iokixkir":["eukayy","Kay Designs too "],
"umgnssd7onlnemki6txuqzif":["eukish","eukish"],
"53icw564wj22fgpzuigqkcza":["eukaryote","Phodog"],
"gvu327xys4nxqvclcxunt5fk":"eukhrst",
"mzcwtvd2k5fnzi4eibyzkpbc":["eukaryotex","Eukaryote"],
"eow7qv4g52e3kychlbbd7pui":["eukie","Eukie"],
"6foznjtzqhbq2o6rjdoudcxs":["eukimya","Kimya"],
"4jnhc3lncaeyw3rzvmna22uw":"eukeitimaria",
"5jbgtdznjapsntcwowbfm4tj":"eukeli",
"gu36xl6evozfnlwskwihub66":["euken","Renato"],
"fjuerhn6nschqqihsbtetony":["eukeupeuti","Eukeupeuti "],
"aiiacmsd6lszu5z3bibyhmbz":"eukat",
"uwhngp44tmuo3i47ygbz2kmc":["eukaryot","Eukaryot"],
"aim4fg5mxei4sezvgtndfqxv":["eukakoala","olivia"],
"qpwpx5zm2pyj72uqtd7tjffu":["eukakrypto","Jazzy Jess"],
"mfknnaiwhmr6st6dgajhhk2e":["eukaliptusderana","EukaDerana"],
"sd5scvmrutudu2zn743tczyi":"eukni",
"zkjnxqj4h3shbjsjofnpusj5":["eukrasian","junebug"],
"4vz7i3xc3wkrpes3iwc75ntv":["eukefrank","Euke Frank"],
"ntdpdnz7vvcbgfkesoj2vp4h":"eukaina",
"fdwnc72fnl2xz3v76a4vyxvx":["karolalmeida","Eukarol_almeida📖"]
}
