{
"54bcf6wxvkcu5hmdfp5jlmvl":"amirho3eyn",
"boa5pow3reloxf4tfdfj4kgm":["erialke","Claire Eyneth"],
"5hvrpvma55c4mnklnww2qufy":["eyneid","Dienye•❌Benimaru⭕️"],
"lcavcgakjeucwy52vjj7oq6b":["eyn","Eyn"],
"k57tsmjuicq2djx4fve7h4ik":"eynsoph",
"vv5x56uhurfa5nmdzwcmjihl":["eynsa","Eve"],
"l7keteuxitrscu3ko4zqfuoh":["eynsinth","Lukas"],
"dipgftarses5t5f3fyz4usw7":["eynimor","EyNimor"],
"z45u3azdslqnvxokuxlvqgye":["eyntkinfo","EYNTKinfo"],
"w6r62bm6k4iggtjtmkdc5pdg":["eynwnrhmujurum","にーたん"],
"wh6z2xp3neng5mdhwrj4arki":["eynk","Yanko Andreev"],
"lt3gd7lki2fa4syvsjub4rie":["eynerd","Eynerd"],
"vualh7y74uwq6xgobrt5s4zd":["eynue","eun 🌼"],
"dakhyp7fpldudhrbgzhh7a7h":["eyndepenal","Andreu Van den Eynde"],
"ta4vzjiwxrmh7er3agrvrx6w":"n8eyn8",
"mhblk2byyg2yoqzyhacogfc2":["nhz","Khare eynaki"],
"x3cuwmxf76niqyomm3xaja5r":["pvaneynd","Peter Van Eynde"],
"awh3niglrsb676hxqbffaiai":["roseofavalon","Rev. Rose Vanden Eynden"],
"xb7jd4ozt2mqeccz3lvxk4oo":["suzyeynon","Suzy Eynon"],
"3l6scnlrbmuz7ljwv3kpqr62":["thraska","Thraska Eynzevar"],
"uhebxq7jlwthrpy3ltmekcof":["valentineynac","Valentin Eynac"]
}
